[
   {
      "name":"Neeltje de",
      "surname":"Graaf",
      "gender":"female",
      "region":"Netherlands"
   },
   {
      "name":"Jan",
      "surname":"Vink",
      "gender":"male",
      "region":"Netherlands"
   },
   {
      "name":"Michiel de",
      "surname":"Leeuw",
      "gender":"male",
      "region":"Netherlands"
   },
   {
      "name":"Geert",
      "surname":"Gerritsen",
      "gender":"male",
      "region":"Netherlands"
   },
   {
      "name":"Willemijn",
      "surname":"Smit",
      "gender":"female",
      "region":"Netherlands"
   },
   {
      "name":"Kees",
      "surname":"Mulder",
      "gender":"male",
      "region":"Netherlands"
   },
   {
      "name":"Nelleke",
      "surname":"Huisman",
      "gender":"female",
      "region":"Netherlands"
   },
   {
      "name":"Leentje",
      "surname":"Maas",
      "gender":"female",
      "region":"Netherlands"
   },
   {
      "name":"Stefan",
      "surname":"Kok",
      "gender":"male",
      "region":"Netherlands"
   },
   {
      "name":"Yasmijn van",
      "surname":"Veen",
      "gender":"female",
      "region":"Netherlands"
   },
   {
      "name":"Doortje de",
      "surname":"Bruijn",
      "gender":"female",
      "region":"Netherlands"
   },
   {
      "name":"Peter de",
      "surname":"Leeuw",
      "gender":"male",
      "region":"Netherlands"
   },
   {
      "name":"Roos",
      "surname":"Willems",
      "gender":"female",
      "region":"Netherlands"
   },
   {
      "name":"Bart",
      "surname":"Mol",
      "gender":"male",
      "region":"Netherlands"
   },
   {
      "name":"Imke van",
      "surname":"Dongen",
      "gender":"female",
      "region":"Netherlands"
   },
   {
      "name":"Mark",
      "surname":"Vos",
      "gender":"male",
      "region":"Netherlands"
   },
   {
      "name":"Tom",
      "surname":"Smits",
      "gender":"male",
      "region":"Netherlands"
   },
   {
      "name":"Laura",
      "surname":"Molenaar",
      "gender":"female",
      "region":"Netherlands"
   },
   {
      "name":"Maaike",
      "surname":"Smit",
      "gender":"female",
      "region":"Netherlands"
   },
   {
      "name":"Gerard",
      "surname":"Prins",
      "gender":"male",
      "region":"Netherlands"
   },
   {
      "name":"Carlijn",
      "surname":"Postma",
      "gender":"female",
      "region":"Netherlands"
   },
   {
      "name":"Carlijn",
      "surname":"Maas",
      "gender":"female",
      "region":"Netherlands"
   },
   {
      "name":"Luuk de",
      "surname":"Haan",
      "gender":"male",
      "region":"Netherlands"
   },
   {
      "name":"Thomas van der",
      "surname":"Heijden",
      "gender":"male",
      "region":"Netherlands"
   },
   {
      "name":"Vincent de",
      "surname":"Lange",
      "gender":"male",
      "region":"Netherlands"
   },
   {
      "name":"Renske",
      "surname":"Hoekstra",
      "gender":"female",
      "region":"Netherlands"
   },
   {
      "name":"Elise",
      "surname":"Vermeulen",
      "gender":"female",
      "region":"Netherlands"
   },
   {
      "name":"Wies de",
      "surname":"Jong",
      "gender":"female",
      "region":"Netherlands"
   },
   {
      "name":"Lisa",
      "surname":"Vos",
      "gender":"female",
      "region":"Netherlands"
   },
   {
      "name":"Femke van",
      "surname":"Dongen",
      "gender":"female",
      "region":"Netherlands"
   },
   {
      "name":"Gerard",
      "surname":"Willems",
      "gender":"male",
      "region":"Netherlands"
   },
   {
      "name":"Peter",
      "surname":"Dekker",
      "gender":"male",
      "region":"Netherlands"
   },
   {
      "name":"Noortje de",
      "surname":"Bruijn",
      "gender":"female",
      "region":"Netherlands"
   },
   {
      "name":"Luuk de",
      "surname":"Boer",
      "gender":"male",
      "region":"Netherlands"
   },
   {
      "name":"Tineke",
      "surname":"Dekker",
      "gender":"female",
      "region":"Netherlands"
   },
   {
      "name":"Florus van den",
      "surname":"Broek",
      "gender":"male",
      "region":"Netherlands"
   },
   {
      "name":"Willemijn",
      "surname":"Hermans",
      "gender":"female",
      "region":"Netherlands"
   },
   {
      "name":"Tineke",
      "surname":"Meijer",
      "gender":"female",
      "region":"Netherlands"
   },
   {
      "name":"Dirk",
      "surname":"Smit",
      "gender":"male",
      "region":"Netherlands"
   },
   {
      "name":"Luuk van",
      "surname":"Dongen",
      "gender":"male",
      "region":"Netherlands"
   },
   {
      "name":"Stefan",
      "surname":"Mol",
      "gender":"male",
      "region":"Netherlands"
   },
   {
      "name":"Freek van",
      "surname":"Dijk",
      "gender":"male",
      "region":"Netherlands"
   },
   {
      "name":"Mathijs",
      "surname":"Mulder",
      "gender":"male",
      "region":"Netherlands"
   },
   {
      "name":"Christiaan",
      "surname":"Maas",
      "gender":"male",
      "region":"Netherlands"
   },
   {
      "name":"Willeke",
      "surname":"Brouwer",
      "gender":"female",
      "region":"Netherlands"
   },
   {
      "name":"Wouter",
      "surname":"Post",
      "gender":"male",
      "region":"Netherlands"
   },
   {
      "name":"Camiel",
      "surname":"Koster",
      "gender":"male",
      "region":"Netherlands"
   },
   {
      "name":"Gerrit van den",
      "surname":"Broek",
      "gender":"male",
      "region":"Netherlands"
   },
   {
      "name":"Teun",
      "surname":"Peters",
      "gender":"male",
      "region":"Netherlands"
   },
   {
      "name":"Mirthe",
      "surname":"Sanders",
      "gender":"female",
      "region":"Netherlands"
   }
]